{
  "colors": {
    "credits": "https://gist.github.com/thomasbnt/b6f455e2c7d743b796917fa3c205f812#file-code_colors_discordjs-md",
    "discord": {
      "BURPLE":    "#5865F2",
      "GREYPLE":   "#99AAB5",
      "DARK1":     "#2C2F33",
      "DARK2":     "#23272A",
      "GREEN":     "#57F287",
      "YELLOW":    "#FEE75C",
      "FUSCHIA":   "#EB459E",
      "RED":       "#ED4245",
      "BLACK":     "#23272A"
    },
    "DEFAULT":     "#000000",
    "WHITE":       "#FFFFFF",
    "AQUA":        "#1ABC9C",
    "DARK_AQUA":   "#11806A",
    "GREEN":       "#2ECC71",
    "DARK_GREEN":  "#1F8B4C",
    "BLUE":        "#3498DB",
    "DARK_BLUE":   "#206694",
    "PURPLE":      "#9B59B6",
    "DARK_PURPLE": "#71368A",
    "LUMINOUS_VIVID_PINK": "#E91E63",
    "DARK_VIVID_PINK": "#AD1457",
    "GOLD":        "#F1C40F",
    "DARK_GOLD":   "#C27C0E",
    "ORANGE":      "#E67E22",
    "DARK_ORANGE": "#A84300",
    "RED":         "#E74C3C",
    "DARK_RED":    "#992D22",
    "GREY":        "#95A5A6",
    "DARK_GREY":   "#979C9F",
    "DARKER_GREY": "#7F8C8D",
    "LIGHT_GREY":  "#BCC0C0",
    "NAVY":        "#34495E",
    "DARK_NAVY":   "#2C3E50",
    "YELLOW":      "#FFFF00"
  }
}